fmc_openapi/__init__.py
fmc_openapi/auth.py
fmc_openapi/client.py
fmc_openapi/exceptions.py
fmc_openapi/executor.py
fmc_openapi/swagger.py
fmc_openapi/utils.py
fmc_openapi-0.1.3.dist-info/LICENSE
fmc_openapi-0.1.3.dist-info/METADATA
fmc_openapi-0.1.3.dist-info/WHEEL
fmc_openapi-0.1.3.dist-info/RECORD
