Metadata-Version: 2.3
Name: fmc_openapi
Version: 0.1.3
Summary: A simple Python client to interact with Cisco FMC or SCC APIs using operationId from the OpenAPI spec.
License: GPL-3.0-only
Keywords: Cisco,FMC,SCC,API,Swagger,OpenAPI,automation
Author: Israel Fernandez
Author-email: israelfdzhdz@gmail.com
Requires-Python: >=3.11
Classifier: License :: OSI Approved :: GNU General Public License v3 (GPLv3)
Classifier: Programming Language :: Python :: 3
Classifier: Programming Language :: Python :: 3.11
Classifier: Programming Language :: Python :: 3.12
Classifier: Programming Language :: Python :: 3.13
Requires-Dist: requests (>=2.32.3,<3.0.0)
Project-URL: Repository, https://github.com/isrferna/fmc_openapi
